README.md
setup.cfg
setup.py
TOPSIS_Arjun_101816046/topsis.py
TOPSIS_Arjun_101816046.egg-info/PKG-INFO
TOPSIS_Arjun_101816046.egg-info/SOURCES.txt
TOPSIS_Arjun_101816046.egg-info/dependency_links.txt
TOPSIS_Arjun_101816046.egg-info/entry_points.txt
TOPSIS_Arjun_101816046.egg-info/requires.txt
TOPSIS_Arjun_101816046.egg-info/top_level.txt